cli.py
greeks.py
tests/__init__.py
tests/test_binomial.py
tests/test_greeks.py
quant_greeks_cli-1.1.0.dist-info/METADATA
quant_greeks_cli-1.1.0.dist-info/WHEEL
quant_greeks_cli-1.1.0.dist-info/entry_points.txt
quant_greeks_cli-1.1.0.dist-info/top_level.txt
quant_greeks_cli-1.1.0.dist-info/RECORD
